setup.py
nickmab/__init__.py
nickmab.async_util.egg-info/PKG-INFO
nickmab.async_util.egg-info/SOURCES.txt
nickmab.async_util.egg-info/dependency_links.txt
nickmab.async_util.egg-info/namespace_packages.txt
nickmab.async_util.egg-info/requires.txt
nickmab.async_util.egg-info/top_level.txt
nickmab/async_util/__init__.py
nickmab/async_util/_exceptions.py
nickmab/async_util/_utils.py
nickmab/async_util/subprocs.py
nickmab/async_util/threads.py
nickmab/async_util/web.py