Metadata-Version: 1.0
Name: nickmab.async-util
Version: 1.1.2
Summary: My first package (be nice please!). Convenience objects for working with long-running calcs and web requests.
Home-page: https://github.com/nickmab/async_util
Author: Nick Mabbutt
Author-email: nickmab@gmail.com
License: MIT
Keywords: json thread async
Platform: UNKNOWN
